jdv_funcutils/__init__.py
jdv_funcutils/__version__.py
jdv_funcutils/imports.py
jdv_funcutils/signature/__init__.py
jdv_funcutils/signature/mutable_signature.py
jdv_funcutils/signature/typedefs.py
jdv_funcutils/signature/utils.py
jdv_funcutils/utils/__init__.py
jdv_funcutils/utils/decorators.py
jdv_funcutils/utils/null.py
jdv_funcutils/utils/repr_utils.py
jdv_funcutils/utils/singleton.py
jdv_funcutils/utils/textutils.py
jdv_funcutils-1.0.2.dist-info/LICENSE.md
jdv_funcutils-1.0.2.dist-info/WHEEL
jdv_funcutils-1.0.2.dist-info/METADATA
jdv_funcutils-1.0.2.dist-info/RECORD
